rag_classic_ml/.ipynb_checkpoints/ClusteringSurvival-checkpoint.py
rag_classic_ml/.ipynb_checkpoints/__main__-checkpoint.py
rag_classic_ml/.ipynb_checkpoints/autoencoder-checkpoint.py
rag_classic_ml/.ipynb_checkpoints/benchmark_ml-checkpoint.py
rag_classic_ml/.ipynb_checkpoints/classification_model_stability_test-checkpoint.py
rag_classic_ml/.ipynb_checkpoints/make_plots-checkpoint.py
rag_classic_ml/.ipynb_checkpoints/make_temp_data-checkpoint.py
rag_classic_ml/.ipynb_checkpoints/pre_processing-checkpoint.py
rag_classic_ml/.ipynb_checkpoints/result_process-checkpoint.py
rag_classic_ml/.ipynb_checkpoints/temp_dataset-checkpoint.csv
rag_classic_ml/.ipynb_checkpoints/train_autoencoder-checkpoint.py
rag_classic_ml/ClusteringSurvival.py
rag_classic_ml/__init__.py
rag_classic_ml/__main__.py
rag_classic_ml/autoencoder.py
rag_classic_ml/base_classification_ml.py
rag_classic_ml/classification_ml.py
rag_classic_ml/classification_model_stability_test.py
rag_classic_ml/evaluate_extract_ae.py
rag_classic_ml/make_plots.py
rag_classic_ml/make_temp_data.py
rag_classic_ml/pre_processing.py
rag_classic_ml/predict_clusters.py
rag_classic_ml/predict_clusters_temp.py
rag_classic_ml/process_clustered_data.py
rag_classic_ml/result_process.py
rag_classic_ml/temp_dataset.csv
rag_classic_ml/train_autoencoder.py
rag_classic_ml-0.1.4.dist-info/LICENSE
rag_classic_ml-0.1.4.dist-info/METADATA
rag_classic_ml-0.1.4.dist-info/WHEEL
rag_classic_ml-0.1.4.dist-info/entry_points.txt
rag_classic_ml-0.1.4.dist-info/RECORD
