Metadata-Version: 2.1
Name: rag-classic-ml
Version: 0.1.4
Summary: Classical Machine Learning methods for Reterival Augmented Generation
Author: VatsalPatel18
Author-email: vatsal1804@gmail.com
Requires-Python: >=3.9,<4.0
Classifier: Programming Language :: Python :: 3
Classifier: Programming Language :: Python :: 3.9
Classifier: Programming Language :: Python :: 3.10
Classifier: Programming Language :: Python :: 3.11
Classifier: Programming Language :: Python :: 3.12
Requires-Dist: lifelines (>=0.27.0,<0.28.0)
Requires-Dist: matplotlib (>=3.7.0,<4.0.0)
Requires-Dist: numpy (>=1.24.0,<2.0.0)
Requires-Dist: pandas (>=2.0.3,<3.0.0)
Requires-Dist: scikit-learn (>=1.2.2,<2.0.0)
Requires-Dist: seaborn (>=0.11.2,<0.12.0)
Requires-Dist: tensorflow (>=2.17.0,<3.0.0)
Requires-Dist: yellowbrick (>=1.5,<2.0)
